{
  "id": 1079,
  "name": "יסמין פרידמן",
  "fullTitle": "חברת הכנסת יסמין פרידמן",
  "faction": "יש עתיד",
  "email": "yfridman@knesset.gov.il",
  "workPhone": "02-6408004",
  "homePhone": null,
  "fax": null,
  "socialLinks": {
    "facebook": null,
    "twitter": null,
    "instagram": null,
    "youtube": null,
    "website": null
  },
  "videoId": null,
  "images": {
    "profile": "https://fs.knesset.gov.il/globaldocs/MK/1079/1_1079_3_17943.jpeg?v=20260415_30372",
    "lobby": "https://fs.knesset.gov.il/globaldocs/MK/1079/1_1079_3_17943.jpeg?v=20260415_30372",
    "banner": "https://fs.knesset.gov.il/globaldocs/MK/1079/1_1079_1_18089.png?v=20260415_30372",
    "bannerMobile": "https://fs.knesset.gov.il/globaldocs/MK/1079/1_1079_4_18090.png?v=20260415_30372"
  },
  "gender": "female",
  "dateOfBirth": "י\"ב בסיוון תשל\"ג , 12/06/1973",
  "deathDate": null,
  "placeOfBirth": "באר שבע, ישראל",
  "immigrationYear": null,
  "residence": "באר שבע",
  "education": "- תואר ראשון במינהל ציבורי, האוניברסיטה הפתוחה \n- בוגרת מכון מנדל למנהיגות בנגב",
  "militaryService": null,
  "nationalService": null,
  "profession": null,
  "languages": [],
  "bio": "יסמין סאקס פרידמן, בת 48, נולדה ומתגוררת בבאר שבע. פעילה ותיקה למען קידום זכויות בעלי החיים ומובילה מאבקים למען דיור ציבורי. \n\nיסמין הייתה חברת מועצת עיריית באר שבע משנת 2013 מטעם סיעת אור. לפני הבחירות למועצת העיר ב-2018 הקימה את סיעת קהילה, והייתה לאישה הראשונה בבאר שבע שעומדת בראשות סיעה המכהנת במועצה.\n\nבעירייה עמדה בראש הוועדה העירונית לאיכות הסביבה ובעלי חיים.\n\nיסמין יזמה את הקמת המרפאה העירונית הראשונה בישראל לחיות רחוב. כמו כן יזמה מבצעים לטובת בעלי החיים בעיר, ובמקביל סייעה למשפחות מעוטות יכולת.\n\nאת דרכה במפלגת יש עתיד החלה עם הקמתה. היא הצטרפה לפעילות המפלגתית, ובהמשך מונתה למנהלת מחוז באר שבע.\n\nיסמין פעילה רבות בנושא הדיור הציבורי בישראל ואף הובילה מאבק להשבת 53 דירות שהיו בהחזקת אוניברסיטת בן-גוריון לזכאי הדיור הציבורי.\n\nבבחירות לכנסת העשרים-וארבע הוצבה במקום ה-19 ברשימת יש עתיד, ובמסגרת החוק הנורבגי הושבעה כחברה בכנסת העשרים-וארבע.\n\nליסמין תואר ראשון במינהל ציבורי מטעם האוניברסיטה הפתוחה, והיא בוגרת מכון מנדל למנהיגות בנגב. \n\nהיא נשואה לשרון ואימו של בר.\n\nצמחונית משנת 2013, ולאחרונה עברה לטבעונות.\n\n\nאפשר לקרוא את קורות החיים של חברי הכנסת גם באתרי הכנסת בשפה הערבית והאנגלית.",
  "knessetId": 25,
  "plenumSeatNumber": "51",
  "isCurrentMk": true,
  "isPresent": false,
  "position": "יושבת-ראש הוועדה המיוחדת לטיפול בשורדי השואה",
  "knessetsList": [],
  "photos": [
    {
      "id": 0,
      "filename": "profile.jpg",
      "localPath": "photos/1079/profile.jpg",
      "originalUrl": "https://fs.knesset.gov.il/globaldocs/MK/1079/1_1079_3_17943.jpeg?v=20260415_30372",
      "width": 0,
      "height": 0,
      "title": "Profile Image"
    },
    {
      "id": 8855,
      "filename": "NOAM1874.JPG",
      "localPath": "photos/1079/NOAM1874.JPG",
      "originalUrl": "/mk/MKPersonalDetailsImages/1079/NOAM1874.JPG",
      "width": 4898,
      "height": 3265,
      "title": "חברת הכנסת יסמין פרידמן בוועדת הכלכלה, 2.8.2021. צילום: נועם מושקוביץ, דוברות הכנסת"
    },
    {
      "id": 8856,
      "filename": "NOAM7377.JPG",
      "localPath": "photos/1079/NOAM7377.JPG",
      "originalUrl": "/mk/MKPersonalDetailsImages/1079/NOAM7377.JPG",
      "width": 5808,
      "height": 3872,
      "title": "חברי הכנסת יסמין פרידמן ושמחה רוטמן בוועדת המסדרת, 12.7.2021. צילום: נועם מושקוביץ, דוברות הכנסת"
    },
    {
      "id": 8857,
      "filename": "NOAM9524.JPG",
      "localPath": "photos/1079/NOAM9524.JPG",
      "originalUrl": "/mk/MKPersonalDetailsImages/1079/NOAM9524.JPG",
      "width": 4464,
      "height": 2976,
      "title": "חברת הכנסת יסמין פרידמן מצהירה אמונים במליאת הכנסת, 16.6.2021. צילום: נועם מושקוביץ, דוברות הכנסת"
    },
    {
      "id": 8859,
      "filename": "DST01918A.JPG",
      "localPath": "photos/1079/DST01918A.JPG",
      "originalUrl": "/mk/MKPersonalDetailsImages/1079/DST01918A.JPG",
      "width": 6000,
      "height": 4000,
      "title": "חברת הכנסת יסמין פרידמן במליאת הכנסת, 13.12.2021. צילום: דני שם-טוב, דוברות הכנסת"
    },
    {
      "id": 8860,
      "filename": "NOAM9488.JPG",
      "localPath": "photos/1079/NOAM9488.JPG",
      "originalUrl": "/mk/MKPersonalDetailsImages/1079/NOAM9488.JPG",
      "width": 5808,
      "height": 3872,
      "title": "חברת הכנסת יסמין פרידמן בנאום הבכורה במליאת הכנסת, 20.72021. צילום: נועם מושקוביץ, דוברות הכנסת"
    },
    {
      "id": 8861,
      "filename": "NOAM9535.JPG",
      "localPath": "photos/1079/NOAM9535.JPG",
      "originalUrl": "/mk/MKPersonalDetailsImages/1079/NOAM9535.JPG",
      "width": 5808,
      "height": 3872,
      "title": "חברת הכנסת יסמין פרידמן בנאום הבכורה במליאת הכנסת, 20.72021. צילום: נועם מושקוביץ, דוברות הכנסת"
    },
    {
      "id": 8862,
      "filename": "NOAM9547.JPG",
      "localPath": "photos/1079/NOAM9547.JPG",
      "originalUrl": "/mk/MKPersonalDetailsImages/1079/NOAM9547.JPG",
      "width": 5808,
      "height": 3872,
      "title": "חברת הכנסת יסמין פרידמן בנאום הבכורה במליאת הכנסת, 20.72021. צילום: נועם מושקוביץ, דוברות הכנסת"
    },
    {
      "id": 8863,
      "filename": "NOAM2888.JPG",
      "localPath": "photos/1079/NOAM2888.JPG",
      "originalUrl": "/mk/MKPersonalDetailsImages/1079/NOAM2888.JPG",
      "width": 5808,
      "height": 3872,
      "title": "חברי הכנסת יסמין פרידמן ויוראי להב הרצנו במליאת הכנסת, 30.6.2021. צילום: נועם מושקוביץ, דוברות הכנסת"
    },
    {
      "id": 8864,
      "filename": "DST07138.JPG",
      "localPath": "photos/1079/DST07138.JPG",
      "originalUrl": "/mk/MKPersonalDetailsImages/1079/DST07138.JPG",
      "width": 6000,
      "height": 4000,
      "title": "חברת הכנסת יסמין פרידמן במליאת הכנסת, 5.1.2022. צילום: דני שם-טוב, דוברות הכנסת"
    },
    {
      "id": 8918,
      "filename": "DST05933.JPG",
      "localPath": "photos/1079/DST05933.JPG",
      "originalUrl": "/mk/MKPersonalDetailsImages/1079/DST05933.JPG",
      "width": 2176,
      "height": 1450,
      "title": "חברת הכנסת יסמין פרידמן בוועדת הפנים והגנת הסביבה, 25.1.2022. צילום: דני שם-טוב, דוברות הכנסת"
    },
    {
      "id": 8970,
      "filename": "20220131113942_NOAM8061.jpg",
      "localPath": "photos/1079/20220131113942_NOAM8061.jpg",
      "originalUrl": "/mk/MKPersonalDetailsImages/1079/20220131113942_NOAM8061.jpg",
      "width": 5808,
      "height": 3872,
      "title": "חברת הכנסת יסמין פרידמן  בוועדה לקידום מעמד האישה, 31.1.2022. צילום: נועם מושקוביץ, דוברות הכנסת"
    },
    {
      "id": 9171,
      "filename": "20220327133213_NOAM4670.jpg",
      "localPath": "photos/1079/20220327133213_NOAM4670.jpg",
      "originalUrl": "/mk/MKPersonalDetailsImages/1079/20220327133213_NOAM4670.jpg",
      "width": 4990,
      "height": 3385,
      "title": "חברת הכנסת יסמין פרידמן בוועדת החינוך, התרבות והספורט, 27.3.2022. צילום: נועם מושקוביץ, דוברות הכנסת"
    },
    {
      "id": 10013,
      "filename": "DST01728.jpg",
      "localPath": "photos/1079/DST01728.jpg",
      "originalUrl": "/mk/MKPersonalDetailsImages/1079/DST01728.jpg",
      "width": 5284,
      "height": 3523,
      "title": "חברת הכנסת יסמין פרידמן בהשבעת הכנסת ה-25. 15.11.2022. צילום: דני שם-טוב, דוברות הכנסת"
    }
  ],
  "scrapedAt": "2026-04-15T18:56:09.554Z",
  "localImagePath": "photos/1079/profile.jpg"
}